deepl_api/__init__.py
deepl_api/cli.py
deepl_api/doc_api.md
deepl_api/doc_cli.md
deepl_api/exceptions.py
deepl_api-0.2.4.dist-info/entry_points.txt
deepl_api-0.2.4.dist-info/WHEEL
deepl_api-0.2.4.dist-info/METADATA
deepl_api-0.2.4.dist-info/RECORD
