Metadata-Version: 2.1
Name: deepl-api
Version: 0.2.4
Summary: Bindings and a commandline tool for the DeepL REST API (https://www.deepl.com/docs-api/)
Home-page: https://github.com/mgruner/deepl-api-py/
License: MIT
Keywords: deepl,api,translation,ai,machine-learning
Author: Martin Gruner
Author-email: mg.pub@gmx.net
Requires-Python: >=3.7,<4.0
Classifier: License :: OSI Approved :: MIT License
Classifier: Programming Language :: Python :: 3
Classifier: Programming Language :: Python :: 3.7
Classifier: Programming Language :: Python :: 3.8
Classifier: Programming Language :: Python :: 3.9
Requires-Dist: click (>=7.1.2)
Requires-Dist: requests (>=2.25,<3.0)
Project-URL: Documentation, https://mgruner.github.io/deepl-api-py-docs/deepl_api/index.html
Project-URL: Repository, https://github.com/mgruner/deepl-api-py/
